pace_calc/__init__.py
pace_calc/converts.py
pace_calc/utils.py
pace_calc-1.0.1.dist-info/LICENSE
pace_calc-1.0.1.dist-info/METADATA
pace_calc-1.0.1.dist-info/WHEEL
pace_calc-1.0.1.dist-info/top_level.txt
pace_calc-1.0.1.dist-info/RECORD
