Metadata-Version: 2.1
Name: pace-calc
Version: 1.0.1
Summary: Библиотека для расчета темпа бега, скорости и времени
Home-page: https://github.com/ntymko/pace_calc
Author: ntymko
Author-email: ndilkova28@gmail.com
License: UNKNOWN
Project-URL: GitHub, https://github.com/ntymko/pace_calc
Keywords: pace calc
Platform: UNKNOWN
Classifier: Programming Language :: Python :: 3.6
Classifier: License :: OSI Approved :: MIT License
Classifier: Operating System :: OS Independent
Requires-Python: >=3.6
License-File: LICENSE
